README.rst
setup.py
extension_logger/__init__.py
extension_logger/extension_logger.py
github/__init__.py
github/extension/__init__.py
github/extension/github.py
github/static/__init__.py
pppextensions.egg-info/PKG-INFO
pppextensions.egg-info/SOURCES.txt
pppextensions.egg-info/dependency_links.txt
pppextensions.egg-info/requires.txt
pppextensions.egg-info/top_level.txt