Metadata-Version: 1.1
Name: pppextensions
Version: 0.0.2
Summary: Extenions - Set of iPython and Jupyter extensions
Home-page: https://github.com/qwjlegend/ppextensions
Author: Extensions Development Team
Author-email: qwjlegend@gmail.com
License: BSD License
Download-URL: https://github.com/qwjlegend/ppextensions
Platform: UNKNOWN
Classifier: Intended Audience :: System Administrators
Classifier: Intended Audience :: Science/Research
Classifier: License :: OSI Approved :: BSD License
Classifier: Programming Language :: Python
Classifier: Programming Language :: Python :: 2
Classifier: Programming Language :: Python :: 2.7
Classifier: Programming Language :: Python :: 3
Classifier: Programming Language :: Python :: 3.3
Classifier: Programming Language :: Python :: 3.4
Classifier: Programming Language :: Python :: 3.5
